stsci/stimage/__init__.py
stsci/stimage/_stimage.cp39-win_amd64.pyd
stsci/stimage/_version.py
stsci_stimage-0.3.0.dist-info/LICENSE
stsci_stimage-0.3.0.dist-info/METADATA
stsci_stimage-0.3.0.dist-info/WHEEL
stsci_stimage-0.3.0.dist-info/top_level.txt
stsci_stimage-0.3.0.dist-info/RECORD
