Metadata-Version: 2.2
Name: stsci.stimage
Version: 0.3.0
Summary: Various image processing functions
Author-email: STScI <help@stsci.edu>
License: Copyright (C) 2008-2025 Association of Universities for Research in Astronomy (AURA)
Project-URL: Tracker, https://github.com/spacetelescope/stsci.stimage/issues
Project-URL: Documentation, https://stscistimage.readthedocs.io/en/latest/
Project-URL: Source Code, https://github.com/spacetelescope/stsci.stimage
Classifier: Intended Audience :: Science/Research
Classifier: License :: OSI Approved :: BSD License
Classifier: Operating System :: OS Independent
Classifier: Programming Language :: Python
Classifier: Topic :: Scientific/Engineering :: Astronomy
Classifier: Topic :: Software Development :: Libraries :: Python Modules
Requires-Python: >=3.9
License-File: LICENSE
Requires-Dist: numpy>=1.14
Provides-Extra: test
Requires-Dist: pytest; extra == "test"
Requires-Dist: pytest-cov; extra == "test"
Provides-Extra: docs
Requires-Dist: sphinx; extra == "docs"
Requires-Dist: sphinx-automodapi; extra == "docs"
Requires-Dist: sphinx-rtd-theme; extra == "docs"
Requires-Dist: tomli; python_version < "3.11" and extra == "docs"
